sphinxcontrib_plot-1.1.11-py3.12-nspkg.pth
sphinxcontrib/plot.py
sphinxcontrib_plot-1.1.11.dist-info/licenses/LICENSE
sphinxcontrib_plot-1.1.11.dist-info/METADATA
sphinxcontrib_plot-1.1.11.dist-info/WHEEL
sphinxcontrib_plot-1.1.11.dist-info/namespace_packages.txt
sphinxcontrib_plot-1.1.11.dist-info/top_level.txt
sphinxcontrib_plot-1.1.11.dist-info/RECORD
