Metadata-Version: 2.4
Name: sphinxcontrib-plot
Version: 1.1.11
Summary: A sphinx extension to plot graph such as ditaa, gnuplot, pyplot, etc in you sphinx document.
Home-page: https://github.com/stathissideris/sphinxcontrib-plot
Author: Yongping Guo
Author-email: Yongping Guo <guoyoooping@163.com>
License: MIT License
Keywords: sphinx,sphinxcontrib,plot,ditaa,gnuplot,magick
Platform: any
License-File: LICENSE
Requires-Dist: Pillow>=3.0.0
Dynamic: author
Dynamic: home-page
Dynamic: license-file
Dynamic: platform
